laboratorio1/problema3/bcd_4b.sv
module bcd_4b (
    input A0, A1, A2, A3,  // Entradas BCD (A3 = MSB)
    output a, b, c, d, e, f, g  // Salidas para display de ánodo común (0=ON, 1=OFF)
);

// Lógica para cada segmento (ánodo común: 0=encendido, 1=apagado)
// Segmento a (activado para 0,2,3,5,6,7,8,9,A,C,E,F)
assign a = ~(
    (~A3 & ~A2 & ~A1 & ~A0) |  // 0
    (~A3 & ~A2 & A1 & ~A0)  |  // 2
    (~A3 & ~A2 & A1 & A0)   |  // 3
    (~A3 & A2 & ~A1 & A0)    |  // 5
    (~A3 & A2 & A1 & ~A0)    |  // 6
    (~A3 & A2 & A1 & A0)     |  // 7
    (A3 & ~A2 & ~A1 & ~A0)   |  // 8
    (A3 & ~A2 & ~A1 & A0)    |  // 9
    (A3 & ~A2 & A1 & ~A0)    |  // A (10)
    (A3 & A2 & ~A1 & ~A0)    |  // C (12)
    (A3 & A2 & A1 & ~A0)     |  // E (14)
    (A3 & A2 & A1 & A0)        // F (15)
);

// Segmento b (activado para 0,1,2,3,4,7,8,9,A,D)
assign b = ~(
    (~A3 & ~A2 & ~A1 & ~A0) |  // 0
    (~A3 & ~A2 & ~A1 & A0)  |  // 1
    (~A3 & ~A2 & A1 & ~A0)  |  // 2
    (~A3 & ~A2 & A1 & A0)   |  // 3
    (~A3 & A2 & ~A1 & ~A0)  |  // 4
    (~A3 & A2 & A1 & A0)    |  // 7
    (A3 & ~A2 & ~A1 & ~A0)  |  // 8
    (A3 & ~A2 & ~A1 & A0)   |  // 9
    (A3 & ~A2 & A1 & ~A0)   |  // A (10)
    (A3 & A2 & ~A1 & A0)      // D (13)
);

// Segmento c (activado para 0,1,3,4,5,6,7,8,9,A,B,D)
assign c = ~(
    (~A3 & ~A2 & ~A1 & ~A0) |  // 0
    (~A3 & ~A2 & ~A1 & A0)  |  // 1
    (~A3 & ~A2 & A1 & A0)   |  // 3
    (~A3 & A2 & ~A1 & ~A0)  |  // 4
    (~A3 & A2 & ~A1 & A0)   |  // 5
    (~A3 & A2 & A1 & ~A0)   |  // 6
    (~A3 & A2 & A1 & A0)    |  // 7
    (A3 & ~A2 & ~A1 & ~A0)  |  // 8
    (A3 & ~A2 & ~A1 & A0)   |  // 9
    (A3 & ~A2 & A1 & ~A0)   |  // A (10)
    (A3 & ~A2 & A1 & A0)    |  // B (11)
    (A3 & A2 & ~A1 & A0)      // D (13)
);

// Segmento d (activado para 0,2,3,5,6,8,9,B,C,D,E)
assign d = ~(
    (~A3 & ~A2 & ~A1 & ~A0) |  // 0
    (~A3 & ~A2 & A1 & ~A0)  |  // 2
    (~A3 & ~A2 & A1 & A0)   |  // 3
    (~A3 & A2 & ~A1 & A0)   |  // 5
    (~A3 & A2 & A1 & ~A0)   |  // 6
    (A3 & ~A2 & ~A1 & ~A0)  |  // 8
    (A3 & ~A2 & ~A1 & A0)   |  // 9
    (A3 & ~A2 & A1 & A0)    |  // B (11)
    (A3 & A2 & ~A1 & ~A0)   |  // C (12)
    (A3 & A2 & ~A1 & A0)    |  // D (13)
    (A3 & A2 & A1 & ~A0)      // E (14)
);

// Segmento e (activado para 0,2,6,8,A,B,C,D,E,F)
assign e = ~(
    (~A3 & ~A2 & ~A1 & ~A0) |  // 0
	 (~A3 & ~A2 & A1 & ~A0)  |  // 2
    (~A3 & A2 & A1 & ~A0)   |  // 6
    (A3 & ~A2 & ~A1 & ~A0)  |  // 8
    (A3 & ~A2 & A1 & ~A0)   |  // A (10)
    (A3 & ~A2 & A1 & A0)    |  // B (11)
    (A3 & A2 & ~A1 & ~A0)   |  // C (12)
    (A3 & A2 & ~A1 & A0)    |  // D (13)
    (A3 & A2 & A1 & ~A0)    |  // E (14)
    (A3 & A2 & A1 & A0)       // F (15)
);

// Segmento f (activado para 0,4,5,6,8,9,A,B,C,E,F)
assign f = ~(
    (~A3 & ~A2 & ~A1 & ~A0) |  // 0
    (~A3 & A2 & ~A1 & ~A0)  |  // 4
    (~A3 & A2 & ~A1 & A0)   |  // 5
    (~A3 & A2 & A1 & ~A0)   |  // 6
    (A3 & ~A2 & ~A1 & ~A0)  |  // 8
    (A3 & ~A2 & ~A1 & A0)   |  // 9
    (A3 & ~A2 & A1 & ~A0)   |  // A (10)
    (A3 & ~A2 & A1 & A0)    |  // B (11)
    (A3 & A2 & ~A1 & ~A0)   |  // C (12)
    (A3 & A2 & A1 & ~A0)    |  // E (14)
    (A3 & A2 & A1 & A0)       // F (15)
);

// Segmento g (activado para 2,3,4,5,6,8,9,A,B,D,E,F)
assign g = ~(
    (~A3 & ~A2 & A1 & ~A0)  |  // 2
    (~A3 & ~A2 & A1 & A0)   |  // 3
    (~A3 & A2 & ~A1 & ~A0)  |  // 4
    (~A3 & A2 & ~A1 & A0)   |  // 5
    (~A3 & A2 & A1 & ~A0)   |  // 6
    (A3 & ~A2 & ~A1 & ~A0)  |  // 8
    (A3 & ~A2 & ~A1 & A0)   |  // 9
    (A3 & ~A2 & A1 & ~A0)   |  // A (10)
    (A3 & ~A2 & A1 & A0)    |  // B (11)
    (A3 & A2 & ~A1 & A0)    |  // D (13)
    (A3 & A2 & A1 & ~A0)    |  // E (14)
    (A3 & A2 & A1 & A0)       // F (15)
);

endmodule

flip_flop.sv
module flip_flop (
    input  logic D,
    input  logic CLK,
    input  logic PRE,   // activo en bajo
    input  logic CLR,   // activo en bajo
    output logic Q,
    output logic nQ
);

    logic nD, CLK_n;
    logic Sm, Rm, Qm, nQm;   // Señales del latch maestro
    logic Ss, Rs;            // Señales del latch esclavo

    assign nD    = ~D;
    assign CLK_n = ~CLK;

    // Latch maestro (activo con CLK = 0)
    nand (Sm, D,    CLK_n);
    nand (Rm, nD,   CLK_n);
    nand (Qm, Sm,   nQm, PRE);  // PRE activa en bajo
    nand (nQm, Rm,  Qm, CLR);   // CLR activa en bajo

    // Latch esclavo (activo con CLK = 1)
    nand (Ss, Qm,   CLK);
    nand (Rs, nQm,  CLK);
    nand (Q,  Ss,   nQ, PRE);   // PRE activa en bajo
    nand (nQ, Rs,   Q,  CLR);   // CLR activa en bajo

endmodule

contador_6bit.sv
module contador_6bit (
    input  logic btn_clk,    // Botón para incrementar
    input  logic reset,      // Reset asíncrono
    output logic [5:0] count // Salida del contador de 6 bits
);

    logic [5:0] current_count;
    logic [5:0] next_count;
    
    // Asignar la salida directamente desde los flip-flops
    assign count = current_count;
    
    // Lógica combinacional para calcular next_count
    // Esta lógica debe estar separada de los flip-flops
    
    // Generación de carry usando compuertas primitivas
    logic c0, c1, c2, c3, c4;
    
    // Carry chain para incremento
    assign c0 = current_count[0];  // carry para bit 1
    and (c1, c0, current_count[1]);  // carry para bit 2
    and (c2, c1, current_count[2]);  // carry para bit 3
    and (c3, c2, current_count[3]);  // carry para bit 4
    and (c4, c3, current_count[4]);  // carry para bit 5
    
    // Cálculo de next_count usando compuertas primitivas
    not (next_count[0], current_count[0]);  // bit 0 siempre se invierte
    xor (next_count[1], current_count[1], c0);
    xor (next_count[2], current_count[2], c1);
    xor (next_count[3], current_count[3], c2);
    xor (next_count[4], current_count[4], c3);
    xor (next_count[5], current_count[5], c4);
    
    // Flip-flops para almacenar el estado
    flip_flop ff0 (
        .D(next_count[0]),
        .CLK(btn_clk),
        .PRE(1'b1),
        .CLR(~reset),
        .Q(current_count[0]),
        .nQ()
    );
    
    flip_flop ff1 (
        .D(next_count[1]),
        .CLK(btn_clk),
        .PRE(1'b1),
        .CLR(~reset),
        .Q(current_count[1]),
        .nQ()
    );
    
    flip_flop ff2 (
        .D(next_count[2]),
        .CLK(btn_clk),
        .PRE(1'b1),
        .CLR(~reset),
        .Q(current_count[2]),
        .nQ()
    );
    
    flip_flop ff3 (
        .D(next_count[3]),
        .CLK(btn_clk),
        .PRE(1'b1),
        .CLR(~reset),
        .Q(current_count[3]),
        .nQ()
    );
    
    flip_flop ff4 (
        .D(next_count[4]),
        .CLK(btn_clk),
        .PRE(1'b1),
        .CLR(~reset),
        .Q(current_count[4]),
        .nQ()
    );
    
    flip_flop ff5 (
        .D(next_count[5]),
        .CLK(btn_clk),
        .PRE(1'b1),
        .CLR(~reset),
        .Q(current_count[5]),
        .nQ()
    );

endmodule

laboratorio1/problema3/boton_incrementador.sv
module boton_incrementador (
    input  logic clk,        // Reloj del sistema
    input  logic btn_raw,    // Botón sin acondicionar
    input  logic reset,      // Reset
    output logic btn_pulse   // Pulso limpio del botón
);

    logic q0, nq0;  // Salidas del primer flip-flop
    logic q1, nq1;  // Salidas del segundo flip-flop
    logic q2, nq2;  // Salidas del tercer flip-flop
    
    logic reset_n;  // Reset negado (para CLR activo en bajo)
    
    // Negar el reset para usar con CLR (activo en bajo)
    not (reset_n, reset);
    
    // Cadena de 3 flip-flops para sincronizar la señal del botón
    flip_flop ff0 (
        .D(btn_raw),
        .CLK(clk),
        .PRE(1'b1),      // PRE inactivo
        .CLR(reset_n),   // CLR activo cuando reset = 1
        .Q(q0),
        .nQ(nq0)
    );
    
    flip_flop ff1 (
        .D(q0),
        .CLK(clk),
        .PRE(1'b1),
        .CLR(reset_n),
        .Q(q1),
        .nQ(nq1)
    );
    
    flip_flop ff2 (
        .D(q1),
        .CLK(clk),
        .PRE(1'b1),
        .CLR(reset_n),
        .Q(q2),
        .nQ(nq2)
    );
    
    // Detectar flanco de subida: q1 AND (NOT q2)
    // Esto genera un pulso cuando hay transición de 0 a 1
    and (btn_pulse, q1, nq2);

endmodule

laboratorio1/problema3/contador_top.sv
module contador_top (
    input  logic clk,           // Reloj del sistema
    input  logic btn_increment, // Botón para incrementar
    input  logic switch_reset,  // Switch de reset
    output logic [6:0] HEX0,    // Display derecho (4 bits menos significativos)
    output logic [6:0] HEX1     // Display izquierdo (2 bits más significativos)
);

    logic btn_clean;
    logic [5:0] count;
    logic [3:0] lower_4bits;   // Para display derecho
    logic [3:0] upper_2bits;   // Para display izquierdo (extendido a 4 bits)
    
    // Debouncer del botón usando compuertas primitivas
    boton_incrementador debouncer (
        .clk(clk),
        .btn_raw(btn_increment),
        .reset(switch_reset),
        .btn_pulse(btn_clean)
    );
    
    // Contador de 6 bits usando compuertas primitivas
    contador_6bit counter (
        .btn_clk(btn_clean),
        .reset(switch_reset),
        .count(count)
    );
    
    // Separar los bits para los displays
    assign lower_4bits = count[3:0];           // 4 bits menos significativos
    assign upper_2bits = {2'b00, count[5:4]}; // 2 bits más significativos extendidos a 4 bits
    
    // Display derecho - 4 bits menos significativos (0-F)
    bcd_4b display_right (
        .A0(lower_4bits[0]),
        .A1(lower_4bits[1]),
        .A2(lower_4bits[2]),
        .A3(lower_4bits[3]),
        .a(HEX0[6]),
        .b(HEX0[5]),
        .c(HEX0[4]),
        .d(HEX0[3]),
        .e(HEX0[2]),
        .f(HEX0[1]),
        .g(HEX0[0])
    );
    
    // Display izquierdo - 2 bits más significativos (0-3)
    bcd_4b display_left (
        .A0(upper_2bits[0]),
        .A1(upper_2bits[1]),
        .A2(upper_2bits[2]),
        .A3(upper_2bits[3]),
        .a(HEX1[6]),
        .b(HEX1[5]),
        .c(HEX1[4]),
        .d(HEX1[3]),
        .e(HEX1[2]),
        .f(HEX1[1]),
        .g(HEX1[0])
    );

endmodule

laboratorio1/problema3/tb_contador_top.sv
`timescale 1ns/1ps

module tb_contador_top;

  // ===== Señales TB =====
  logic clk;
  logic btn_increment;
  logic switch_reset;
  logic [6:0] HEX0;
  logic [6:0] HEX1;

  // ===== Instancia del DUT =====
  contador_top dut (
    .clk           (clk),
    .btn_increment (btn_increment),
    .switch_reset  (switch_reset),
    .HEX0          (HEX0),
    .HEX1          (HEX1)
  );

  // ===== Taps jerárquicos para debug/verificación =====
 
  wire        btn_clean  = dut.btn_clean;    // pulso limpio del debouncer
  wire [5:0]  count_int  = dut.count;        // valor interno del contador

  // ===== Reloj 100 MHz (Periodo 10ns) =====
  initial clk = 1'b0;
  always #5 clk = ~clk;

  // ===== Utilidades para prueba =====

  // "Pulsación" ideal (sin rebote): mantiene el botón en 1 por N ciclos de clk
  task automatic press_button(input int cycles_high = 10, input int cycles_low = 10);
    begin
      btn_increment = 1'b1;
      repeat (cycles_high) @(posedge clk);
      btn_increment = 1'b0;
      repeat (cycles_low)  @(posedge clk);
    end
  endtask

  // "Pulsación" con rebote simulado: alterna rápido antes de estabilizar
  task automatic press_button_bouncy(
      input int pre_bounce_toggles = 6,
      input int bounce_half_period_cycles = 1,
      input int hold_cycles = 10,
      input int after_low_cycles = 10
  );
    int i;
    begin
      // rebote: alterna rápido
      btn_increment = 1'b0;
      for (i = 0; i < pre_bounce_toggles; i++) begin
        repeat (bounce_half_period_cycles) @(posedge clk);
        btn_increment = ~btn_increment;
      end
      // estabiliza en 1 (botón presionado)
      btn_increment = 1'b1;
      repeat (hold_cycles) @(posedge clk);
      // suelta
      btn_increment = 1'b0;
      repeat (after_low_cycles) @(posedge clk);
    end
  endtask

  // Decodifica 7 segmentos (opcional, común cátodo activo-alto).
  // Si tu bcd_4b usa otra codificación, deja esto solo para imprimir crudo.
  function automatic string seg7_to_str(input logic [6:0] seg);
    // mapea típico: a b c d e f g = [6:0]
    // devuelve un hex (0-F) si coincide con patrón estándar, si no "?"
    case (seg)
      7'b1111110: seg7_to_str = "0";
      7'b0110000: seg7_to_str = "1";
      7'b1101101: seg7_to_str = "2";
      7'b1111001: seg7_to_str = "3";
      7'b0110011: seg7_to_str = "4";
      7'b1011011: seg7_to_str = "5";
      7'b1011111: seg7_to_str = "6";
      7'b1110000: seg7_to_str = "7";
      7'b1111111: seg7_to_str = "8";
      7'b1111011: seg7_to_str = "9";
      7'b1110111: seg7_to_str = "A";
      7'b0011111: seg7_to_str = "b";
      7'b1001110: seg7_to_str = "C";
      7'b0111101: seg7_to_str = "d";
      7'b1001111: seg7_to_str = "E";
      7'b1000111: seg7_to_str = "F";
      default:    seg7_to_str = "?";
    endcase
  endfunction

  // ===== Monitor & Checker =====
  logic [5:0] prev_count;
  logic       prev_clean;

  // Traza textual en cada flanco de clk
  always @(posedge clk) begin
    $display("t=%0t | rst=%0b btn_raw=%0b btn_clean=%0b | count=%0d (0x%0h) | HEX1=%b HEX0=%b | H1:%s H0:%s",
      $time, switch_reset, btn_increment, btn_clean, count_int, count_int,
      HEX1, HEX0, seg7_to_str(HEX1), seg7_to_str(HEX0));
  end

  // Pequeño checker: si hay flanco de subida en btn_clean, count debe incrementar en 1 (mod 64)
  always @(posedge clk) begin
    if (!switch_reset) begin
      if (btn_clean && !prev_clean) begin
        // flanco de subida detectado
        if (count_int !== (prev_count + 6'd1) % 64) begin
          $error("Contador no incrementó correctamente: prev=%0d actual=%0d", prev_count, count_int);
        end
      end
      prev_count <= count_int;
      prev_clean <= btn_clean;
    end else begin
      prev_count <= '0;
      prev_clean <= 1'b0;
    end
  end

  // ===== Estímulos =====
  initial begin
    // VCD (si usas ModelSim/Questa, puedes quedarte con esto o usar wlf)
    $dumpfile("contador_top_tb.vcd");
    $dumpvars(0, tb_contador_top);

    // Inicialización
    btn_increment = 1'b0;
    switch_reset  = 1'b1; // en reset
    prev_count    = '0;
    prev_clean    = 1'b0;

    $display("\n=== INICIO ===");

    // Mantén reset unas cuantas decenas de ns
    repeat (10) @(posedge clk);
    switch_reset = 1'b0; // libera reset
    repeat (10) @(posedge clk);

    // 1) Varias pulsaciones limpias
    $display("\n--- Pulsaciones limpias ---");
    repeat (5) press_button(12, 15);

    // 2) Pulsación con rebote simulado
    $display("\n--- Pulsación con rebote simulado ---");
    press_button_bouncy(8, 1, 12, 15);

    // 3) Ráfaga de pulsos rápidos (para ver si el debouncer filtra)
    $display("\n--- Ráfaga rápida ---");
    repeat (8) press_button(2, 3);

    // 4) Reset en medio y nueva pulsación
    $display("\n--- Reset intermedio ---");
    switch_reset = 1'b1;
    repeat (5) @(posedge clk);
    switch_reset = 1'b0;
    repeat (5) @(posedge clk);
    press_button(12, 10);

    $display("\n=== FIN ===");
    #50;
    $finish;
  end

endmodule

laboratorio1/problema3/simulation/questa/contador_top_tb.vcd
$date
	Fri Aug 22 11:10:11 2025
$end
$version
	ModelSim Version 10.5b
$end
$timescale
	1ps
$end

$scope module tb_contador_top $end
$var reg 1 ! clk $end
$var reg 1 " btn_increment $end
$var reg 1 # switch_reset $end
$var reg 7 $ HEX0 [6:0] $end
$var reg 7 % HEX1 [6:0] $end
$var wire 1 & btn_clean $end
$var wire 1 ' count_int [5] $end
$var wire 1 ( count_int [4] $end
$var wire 1 ) count_int [3] $end
$var wire 1 * count_int [2] $end
$var wire 1 + count_int [1] $end
$var wire 1 , count_int [0] $end
$var reg 6 - prev_count [5:0] $end
$var reg 1 . prev_clean $end

$scope task press_button $end
$upscope $end

$scope task press_button_bouncy $end
$upscope $end

$scope function seg7_to_str $end
$upscope $end

$scope module dut $end
$var wire 1 / clk $end
$var wire 1 0 btn_increment $end
$var wire 1 1 switch_reset $end
$var reg 7 2 HEX0 [6:0] $end
$var reg 7 3 HEX1 [6:0] $end
$var reg 1 4 btn_clean $end
$var reg 6 5 count [5:0] $end
$var reg 4 6 lower_4bits [3:0] $end
$var reg 4 7 upper_2bits [3:0] $end

$scope module debouncer $end
$var wire 1 / clk $end
$var wire 1 0 btn_raw $end
$var wire 1 1 reset $end
$var reg 1 8 btn_pulse $end
$var reg 1 9 q0 $end
$var reg 1 : nq0 $end
$var reg 1 ; q1 $end
$var reg 1 < nq1 $end
$var reg 1 = q2 $end
$var reg 1 > nq2 $end
$var reg 1 ? reset_n $end

$scope module ff0 $end
$var wire 1 0 D $end
$var wire 1 / CLK $end
$var wire 1 @ PRE $end
$var wire 1 A CLR $end
$var reg 1 B Q $end
$var reg 1 C nQ $end
$var reg 1 D nD $end
$var reg 1 E CLK_n $end
$var reg 1 F Sm $end
$var reg 1 G Rm $end
$var reg 1 H Qm $end
$var reg 1 I nQm $end
$var reg 1 J Ss $end
$var reg 1 K Rs $end
$upscope $end

$scope module ff1 $end
$var wire 1 L D $end
$var wire 1 / CLK $end
$var wire 1 M PRE $end
$var wire 1 N CLR $end
$var reg 1 O Q $end
$var reg 1 P nQ $end
$var reg 1 Q nD $end
$var reg 1 R CLK_n $end
$var reg 1 S Sm $end
$var reg 1 T Rm $end
$var reg 1 U Qm $end
$var reg 1 V nQm $end
$var reg 1 W Ss $end
$var reg 1 X Rs $end
$upscope $end

$scope module ff2 $end
$var wire 1 Y D $end
$var wire 1 / CLK $end
$var wire 1 Z PRE $end
$var wire 1 [ CLR $end
$var reg 1 \ Q $end
$var reg 1 ] nQ $end
$var reg 1 ^ nD $end
$var reg 1 _ CLK_n $end
$var reg 1 ` Sm $end
$var reg 1 a Rm $end
$var reg 1 b Qm $end
$var reg 1 c nQm $end
$var reg 1 d Ss $end
$var reg 1 e Rs $end
$upscope $end
$upscope $end

$scope module counter $end
$var wire 1 f btn_clk $end
$var wire 1 1 reset $end
$var reg 6 g count [5:0] $end
$var reg 6 h current_count [5:0] $end
$var reg 6 i next_count [5:0] $end
$var reg 1 j c0 $end
$var reg 1 k c1 $end
$var reg 1 l c2 $end
$var reg 1 m c3 $end
$var reg 1 n c4 $end

$scope module ff0 $end
$var wire 1 o D $end
$var wire 1 f CLK $end
$var wire 1 p PRE $end
$var wire 1 q CLR $end
$var reg 1 r Q $end
$var reg 1 s nQ $end
$var reg 1 t nD $end
$var reg 1 u CLK_n $end
$var reg 1 v Sm $end
$var reg 1 w Rm $end
$var reg 1 x Qm $end
$var reg 1 y nQm $end
$var reg 1 z Ss $end
$var reg 1 { Rs $end
$upscope $end

$scope module ff1 $end
$var wire 1 | D $end
$var wire 1 f CLK $end
$var wire 1 } PRE $end
$var wire 1 ~ CLR $end
$var reg 1 !! Q $end
$var reg 1 "! nQ $end
$var reg 1 #! nD $end
$var reg 1 $! CLK_n $end
$var reg 1 %! Sm $end
$var reg 1 &! Rm $end
$var reg 1 '! Qm $end
$var reg 1 (! nQm $end
$var reg 1 )! Ss $end
$var reg 1 *! Rs $end
$upscope $end

$scope module ff2 $end
$var wire 1 +! D $end
$var wire 1 f CLK $end
$var wire 1 ,! PRE $end
$var wire 1 -! CLR $end
$var reg 1 .! Q $end
$var reg 1 /! nQ $end
$var reg 1 0! nD $end
$var reg 1 1! CLK_n $end
$var reg 1 2! Sm $end
$var reg 1 3! Rm $end
$var reg 1 4! Qm $end
$var reg 1 5! nQm $end
$var reg 1 6! Ss $end
$var reg 1 7! Rs $end
$upscope $end

$scope module ff3 $end
$var wire 1 8! D $end
$var wire 1 f CLK $end
$var wire 1 9! PRE $end
$var wire 1 :! CLR $end
$var reg 1 ;! Q $end
$var reg 1 <! nQ $end
$var reg 1 =! nD $end
$var reg 1 >! CLK_n $end
$var reg 1 ?! Sm $end
$var reg 1 @! Rm $end
$var reg 1 A! Qm $end
$var reg 1 B! nQm $end
$var reg 1 C! Ss $end
$var reg 1 D! Rs $end
$upscope $end

$scope module ff4 $end
$var wire 1 E! D $end
$var wire 1 f CLK $end
$var wire 1 F! PRE $end
$var wire 1 G! CLR $end
$var reg 1 H! Q $end
$var reg 1 I! nQ $end
$var reg 1 J! nD $end
$var reg 1 K! CLK_n $end
$var reg 1 L! Sm $end
$var reg 1 M! Rm $end
$var reg 1 N! Qm $end
$var reg 1 O! nQm $end
$var reg 1 P! Ss $end
$var reg 1 Q! Rs $end
$upscope $end

$scope module ff5 $end
$var wire 1 R! D $end
$var wire 1 f CLK $end
$var wire 1 S! PRE $end
$var wire 1 T! CLR $end
$var reg 1 U! Q $end
$var reg 1 V! nQ $end
$var reg 1 W! nD $end
$var reg 1 X! CLK_n $end
$var reg 1 Y! Sm $end
$var reg 1 Z! Rm $end
$var reg 1 [! Qm $end
$var reg 1 \! nQm $end
$var reg 1 ]! Ss $end
$var reg 1 ^! Rs $end
$upscope $end
$upscope $end

$scope module display_right $end
$var wire 1 _! A0 $end
$var wire 1 `! A1 $end
$var wire 1 a! A2 $end
$var wire 1 b! A3 $end
$var wire 1 c! a $end
$var wire 1 d! b $end
$var wire 1 e! c $end
$var wire 1 f! d $end
$var wire 1 g! e $end
$var wire 1 h! f $end
$var wire 1 i! g $end
$upscope $end

$scope module display_left $end
$var wire 1 j! A0 $end
$var wire 1 k! A1 $end
$var wire 1 l! A2 $end
$var wire 1 m! A3 $end
$var wire 1 n! a $end
$var wire 1 o! b $end
$var wire 1 p! c $end
$var wire 1 q! d $end
$var wire 1 r! e $end
$var wire 1 s! f $end
$var wire 1 t! g $end
$upscope $end
$upscope $end
$upscope $end
$enddefinitions $end
#0
$dumpvars
0!
0"
1#
b1 $
b1 %
b1 2
b1 3
04
b0 5
b0 6
b0 7
08
09
1:
0;
1<
0=
1>
0?
0B
1C
1D
1E
1F
0G
0H
1I
1J
1K
0O
1P
1Q
1R
1S
0T
0U
1V
1W
1X
0\
1]
1^
1_
1`
0a
0b
1c
1d
1e
b0 g
b0 h
b1 i
0j
0k
0l
0m
0n
0r
1s
0t
1u
0v
1w
1x
1y
1z
1{
0!!
1"!
1#!
1$!
1%!
0&!
0'!
1(!
1)!
1*!
0.!
1/!
10!
11!
12!
03!
04!
15!
16!
17!
0;!
1<!
1=!
1>!
1?!
0@!
0A!
1B!
1C!
1D!
0H!
1I!
1J!
1K!
1L!
0M!
0N!
1O!
1P!
1Q!
0U!
1V!
1W!
1X!
1Y!
0Z!
0[!
1\!
1]!
1^!
b0 -
0.
0&
0,
0+
0*
0)
0(
0'
0/
00
11
1Z
1M
1@
0A
0L
0N
0Y
0[
0f
0T!
1S!
0G!
1F!
0:!
19!
0-!
1,!
0~
1}
0q
1p
1o
0|
0+!
08!
0E!
0R!
0_!
0`!
0a!
0b!
0c!
0d!
0e!
0f!
0g!
0h!
1i!
0j!
0k!
0l!
0m!
0n!
0o!
0p!
0q!
0r!
0s!
1t!
$end
#5000
1!
1/
0E
0R
0_
0K
0X
0e
1a
1T
1G
#10000
0!
0/
1E
1R
1_
1K
1X
1e
0a
0T
0G
#15000
1!
1/
0E
0R
0_
0K
0X
0e
1a
1T
1G
#20000
0!
0/
1E
1R
1_
1K
1X
1e
0a
0T
0G
#25000
1!
1/
0E
0R
0_
0K
0X
0e
1a
1T
1G
#30000
0!
0/
1E
1R
1_
1K
1X
1e
0a
0T
0G
#35000
1!
1/
0E
0R
0_
0K
0X
0e
1a
1T
1G
#40000
0!
0/
1E
1R
1_
1K
1X
1e
0a
0T
0G
#45000
1!
1/
0E
0R
0_
0K
0X
0e
1a
1T
1G
#50000
0!
0/
1E
1R
1_
1K
1X
1e
0a
0T
0G
#55000
1!
1/
0E
0R
0_
0K
0X
0e
1a
1T
1G
#60000
0!
0/
1E
1R
1_
1K
1X
1e
0a
0T
0G
#65000
1!
1/
0E
0R
0_
0K
0X
0e
1a
1T
1G
#70000
0!
0/
1E
1R
1_
1K
1X
1e
0a
0T
0G
#75000
1!
1/
0E
0R
0_
0K
0X
0e
1a
1T
1G
#80000
0!
0/
1E
1R
1_
1K
1X
1e
0a
0T
0G
#85000
1!
1/
0E
0R
0_
0K
0X
0e
1a
1T
1G
#90000
0!
0/
1E
1R
1_
1K
1X
1e
0a
0T
0G
#95000
1!
1/
0E
0R
0_
0K
0X
0e
1a
1T
1G
0#
01
1T!
1G!
1:!
1-!
1~
1q
0y
1?
1[
1N
1A
#100000
0!
0/
1E
1R
1_
1K
1X
1e
0a
0T
0G
#105000
1!
1/
0E
0R
0_
0K
0X
0e
1a
1T
1G
#110000
0!
0/
1E
1R
1_
1K
1X
1e
0a
0T
0G
#115000
1!
1/
0E
0R
0_
0K
0X
0e
1a
1T
1G
#120000
0!
0/
1E
1R
1_
1K
1X
1e
0a
0T
0G
#125000
1!
1/
0E
0R
0_
0K
0X
0e
1a
1T
1G
#130000
0!
0/
1E
1R
1_
1K
1X
1e
0a
0T
0G
#135000
1!
1/
0E
0R
0_
0K
0X
0e
1a
1T
1G
#140000
0!
0/
1E
1R
1_
1K
1X
1e
0a
0T
0G
#145000
1!
1/
0E
0R
0_
0K
0X
0e
1a
1T
1G
#150000
0!
0/
1E
1R
1_
1K
1X
1e
0a
0T
0G
#155000
1!
1/
0E
0R
0_
0K
0X
0e
1a
1T
1G
#160000
0!
0/
1E
1R
1_
1K
1X
1e
0a
0T
0G
#165000
1!
1/
0E
0R
0_
0K
0X
0e
1a
1T
1G
#170000
0!
0/
1E
1R
1_
1K
1X
1e
0a
0T
0G
#175000
1!
1/
0E
0R
0_
0K
0X
0e
1a
1T
1G
#180000
0!
0/
1E
1R
1_
1K
1X
1e
0a
0T
0G
#185000
1!
1/
0E
0R
0_
0K
0X
0e
1a
1T
1G
#190000
0!
0/
1E
1R
1_
1K
1X
1e
0a
0T
0G
#195000
1!
1/
0E
0R
0_
0K
0X
0e
1a
1T
1G
1"
10
0D
#200000
0!
0/
1E
1R
1_
1K
1X
1e
0a
0T
0F
1H
0I
#205000
1!
1/
0E
0R
0_
0J
0X
0e
1a
1T
1F
1B
19
1L
0C
0Q
0:
#210000
0!
0/
1E
1R
1_
1J
1X
1e
0a
0S
0F
1U
0V
#215000
1!
1/
0E
0R
0_
0J
0W
0e
1a
1S
1F
1O
1;
1Y
0P
0^
18
0<
14
1&
1f
0u
0$!
01!
0>!
0K!
0X!
0z
0*!
07!
0D!
0Q!
0^!
1Z!
1M!
1@!
13!
1&!
1v
1r
b1 h
b1 g
1j
b0 i
0s
b1 5
b1 6
1,
b10 i
0o
1t
1_!
1c!
1f!
1g!
1h!
b11 2
b111 2
b1111 2
b1001111 2
1|
0#!
b1001111 $
b1 -
1.
#220000
0!
0/
1E
1R
1_
1J
1W
1e
0`
0S
0F
1b
0c
#225000
1!
1/
0E
0R
0_
0J
0W
0d
1`
1S
1F
1\
1=
0]
0>
08
04
0&
0f
1u
1$!
11!
1>!
1K!
1X!
1z
1*!
17!
1D!
1Q!
1^!
0Z!
0M!
0@!
03!
0%!
0w
1y
1'!
0(!
0x
0.
#230000
0!
0/
1E
1R
1_
1J
1W
1d
0`
0S
0F
#235000
1!
1/
0E
0R
0_
0J
0W
0d
1`
1S
1F
#240000
0!
0/
1E
1R
1_
1J
1W
1d
0`
0S
0F
#245000
1!
1/
0E
0R
0_
0J
0W
0d
1`
1S
1F
#250000
0!
0/
1E
1R
1_
1J
1W
1d
0`
0S
0F
#255000
1!
1/
0E
0R
0_
0J
0W
0d
1`
1S
1F
#260000
0!
0/
1E
1R
1_
1J
1W
1d
0`
0S
0F
#265000
1!
1/
0E
0R
0_
0J
0W
0d
1`
1S
1F
#270000
0!
0/
1E
1R
1_
1J
1W
1d
0`
0S
0F
#275000
1!
1/
0E
0R
0_
0J
0W
0d
1`
1S
1F
#280000
0!
0/
1E
1R
1_
1J
1W
1d
0`
0S
0F
#285000
1!
1/
0E
0R
0_
0J
0W
0d
1`
1S
1F
#290000
0!
0/
1E
1R
1_
1J
1W
1d
0`
0S
0F
#295000
1!
1/
0E
0R
0_
0J
0W
0d
1`
1S
1F
#300000
0!
0/
1E
1R
1_
1J
1W
1d
0`
0S
0F
#305000
1!
1/
0E
0R
0_
0J
0W
0d
1`
1S
1F
#310000
0!
0/
1E
1R
1_
1J
1W
1d
0`
0S
0F
#315000
1!
1/
0E
0R
0_
0J
0W
0d
1`
1S
1F
0"
00
1D
#320000
0!
0/
1E
1R
1_
1J
1W
1d
0`
0S
0G
1I
0H
#325000
1!
1/
0E
0R
0_
0K
0W
0d
1`
1S
1G
1C
1:
0B
09
0L
1Q
#330000
0!
0/
1E
1R
1_
1K
1W
1d
0`
0T
0G
1V
0U
#335000
1!
1/
0E
0R
0_
0K
0X
0d
1`
1T
1G
1P
1<
0O
0;
0Y
1^
#340000
0!
0/
1E
1R
1_
1K
1X
1d
0a
0T
0G
1c
0b
